snapinfra/__init__.py
snapinfra/__main__.py
snapinfra/config.py
snapinfra/agents/__init__.py
snapinfra/agents/multi_agent_system.py
snapinfra/backends/__init__.py
snapinfra/backends/bedrock.py
snapinfra/backends/factory.py
snapinfra/backends/groq.py
snapinfra/backends/ollama.py
snapinfra/backends/openai.py
snapinfra/cli/__init__.py
snapinfra/cli/diagram.py
snapinfra/cli/interactive.py
snapinfra/cli/interactive_aac_methods.py
snapinfra/cli/main.py
snapinfra/cli/prompts.py
snapinfra/cli/startup.py
snapinfra/cli/validation.py
snapinfra/config/__init__.py
snapinfra/config/loader.py
snapinfra/config/models.py
snapinfra/diagram/__init__.py
snapinfra/diagram/api_server.py
snapinfra/diagram/models.py
snapinfra/diagram/version_control.py
snapinfra/diagram/viewer_server.py
snapinfra/diagram/generators/__init__.py
snapinfra/diagram/generators/base.py
snapinfra/diagram/generators/d2.py
snapinfra/diagram/generators/mermaid.py
snapinfra/diagram/generators/mingrammer.py
snapinfra/diagram/parsers/__init__.py
snapinfra/diagram/parsers/terraform.py
snapinfra/diagram/renderers/__init__.py
snapinfra/diagram/renderers/kroki_client.py
snapinfra/diagram/templates/viewer.html
snapinfra/prompts/__init__.py
snapinfra/prompts/prompt_builder.py
snapinfra/prompts/system_prompts.py
snapinfra/types/__init__.py
snapinfra/types/exceptions.py
snapinfra/types/interfaces.py
snapinfra/types/models.py
snapinfra/utils/__init__.py
snapinfra/utils/clipboard.py
snapinfra/utils/model_switching.py
snapinfra/utils/spinner.py
snapinfra/validation/__init__.py
snapinfra/validation/architecture.py
snapinfra/validation/auto_fix.py
snapinfra/validation/completeness.py
snapinfra/validation/core.py
snapinfra/validation/imports.py
snapinfra/validation/reporter.py
snapinfra/validation/syntax.py
snapinfra/validation/validators.py
snapinfra/validation/workflow.py
snapinfra-1.1.3.dist-info/licenses/LICENSE
snapinfra-1.1.3.dist-info/METADATA
snapinfra-1.1.3.dist-info/WHEEL
snapinfra-1.1.3.dist-info/entry_points.txt
snapinfra-1.1.3.dist-info/top_level.txt
snapinfra-1.1.3.dist-info/RECORD
