Metadata-Version: 2.4
Name: snapinfra
Version: 1.1.3
Summary: AI-powered CLI that generates infrastructure code and architecture diagrams from natural language. Features interactive progress tracking, syntax-highlighted previews, and automated architecture-first workflow. Supports Terraform, Kubernetes, Docker with multi-provider AI backends.
Author-email: Manoj Maheshwar Jagadeesan <manojmaheshwarjg@gmail.com>
Project-URL: Homepage, https://github.com/manojmaheshwarjg/snapinfra-cli
Project-URL: Documentation, https://github.com/manojmaheshwarjg/snapinfra-cli#readme
Project-URL: Repository, https://github.com/manojmaheshwarjg/snapinfra-cli.git
Project-URL: Bug Reports, https://github.com/manojmaheshwarjg/snapinfra-cli/issues
Keywords: ai,infrastructure,iac,terraform,kubernetes,docker,architecture,cloudformation,llm,openai,groq,bedrock,ollama,code-generation,devops,automation,cli-tool,infrastructure-automation,cloud,aws,azure,gcp,diagrams,mermaid,chat-based,natural-language,ai-powered,production-ready
Classifier: Development Status :: 4 - Beta
Classifier: Environment :: Console
Classifier: Intended Audience :: Developers
Classifier: Intended Audience :: System Administrators
Classifier: Operating System :: OS Independent
Classifier: Programming Language :: Python :: 3
Classifier: Programming Language :: Python :: 3.8
Classifier: Programming Language :: Python :: 3.9
Classifier: Programming Language :: Python :: 3.10
Classifier: Programming Language :: Python :: 3.11
Classifier: Programming Language :: Python :: 3.12
Classifier: Topic :: Software Development :: Code Generators
Classifier: Topic :: System :: Systems Administration
Classifier: Topic :: Scientific/Engineering :: Artificial Intelligence
Requires-Python: >=3.8
License-File: LICENSE
Requires-Dist: click>=8.0.0
Requires-Dist: rich>=13.0.0
Requires-Dist: openai>=1.0.0
Requires-Dist: groq>=0.4.0
Requires-Dist: boto3>=1.34.0
Requires-Dist: httpx>=0.25.0
Requires-Dist: tomli>=2.0.0; python_version < "3.11"
Requires-Dist: toml>=0.10.2
Requires-Dist: pydantic>=2.0.0
Requires-Dist: pyperclip>=1.8.0
Requires-Dist: python-dotenv>=1.0.0
Requires-Dist: platformdirs>=3.0.0
Requires-Dist: aiofiles>=23.0.0
Requires-Dist: typing-extensions>=4.5.0
Requires-Dist: autogen-agentchat>=0.2.0
Requires-Dist: autogen-ext[openai]>=0.2.0
Requires-Dist: diagrams>=0.23.0
Requires-Dist: graphviz>=0.20.0
Requires-Dist: fastapi>=0.104.0
Requires-Dist: uvicorn[standard]>=0.24.0
Requires-Dist: jinja2>=3.1.0
Requires-Dist: websockets>=12.0
Requires-Dist: python-multipart>=0.0.6
Provides-Extra: viewer
Requires-Dist: fastapi>=0.104.0; extra == "viewer"
Requires-Dist: uvicorn[standard]>=0.24.0; extra == "viewer"
Requires-Dist: jinja2>=3.1.0; extra == "viewer"
Requires-Dist: websockets>=12.0; extra == "viewer"
Provides-Extra: dev
Requires-Dist: pytest>=7.0.0; extra == "dev"
Requires-Dist: pytest-cov>=4.0.0; extra == "dev"
Requires-Dist: pytest-asyncio>=0.21.0; extra == "dev"
Requires-Dist: black>=23.0.0; extra == "dev"
Requires-Dist: ruff>=0.1.0; extra == "dev"
Dynamic: license-file
